document_embedding/average.py
document_embedding/base.py
document_embedding/pert.py
document_embedding/sentences.py
document_embedding-0.0.1.dist-info/METADATA
document_embedding-0.0.1.dist-info/WHEEL
document_embedding-0.0.1.dist-info/top_level.txt
document_embedding-0.0.1.dist-info/RECORD
