Metadata-Version: 2.1
Name: document-embedding
Version: 0.0.1
Requires-Dist: numpy
Requires-Dist: numba
Requires-Dist: sentence-transformers
Requires-Dist: torch
Requires-Dist: mcerp
Requires-Dist: nltk
Provides-Extra: dev
Requires-Dist: isort ; extra == 'dev'
Requires-Dist: pytest ; extra == 'dev'
Requires-Dist: rope ; extra == 'dev'
Requires-Dist: toml ; extra == 'dev'
Requires-Dist: yapf ; extra == 'dev'
Provides-Extra: test
Requires-Dist: pytest ; extra == 'test'
